{
    "backend": "flask",
    "db_name": "",
    "db_pass": "",
    "db_type": "",
    "db_user": "",
    "dbms": "0",
    "description": "generated product",
    "design": "datta-able",
    "docker": "0",
    "err_code": 0,
    "frontend": "",
    "heroku": "0",
    "pattern": "mvc",
    "pro": "0",
    "task_id": "70ac1366-f98b-4645-ae1b-672db9bf8e81",
    "task_info": "Upload Sources [0%] - 133 files",
    "task_output": "70ac1366-f98b-4645-ae1b-672db9bf8e81.zip",
    "task_result": "SUCCESS",
    "task_state": "RUNNING",
    "task_ts_end": "2022-12-28-23-32-06",
    "task_ts_start": "2022-12-28-23-32-04"
}